app/__init__.py
app/config.py
app/console_help.py
app/example_config.toml
app/generate_config.py
app/main.py
app/auth/auth.py
app/cache/cache.py
app/cache/rate_limiting.py
app/db/database.py
app/middlewares/example_middleware.py
app/model/models.py
glimapi-0.1.0.dist-info/LICENSE
glimapi-0.1.0.dist-info/METADATA
glimapi-0.1.0.dist-info/WHEEL
glimapi-0.1.0.dist-info/entry_points.txt
glimapi-0.1.0.dist-info/top_level.txt
glimapi-0.1.0.dist-info/RECORD
