Metadata-Version: 2.1
Name: glimapi
Version: 0.1.0
Summary: A dynamic API generator with JWT, rate limiting and localization support.
Home-page: https://github.com/Glimor/glim-api
Author: KAAN KAYACI
Author-email: kayaci.kaan@proton.me
License: CC BY-NC-ND 4.0
License-File: LICENSE
Requires-Dist: fastapi
Requires-Dist: pydantic
Requires-Dist: uvicorn
Requires-Dist: pymongo
Requires-Dist: jose
Requires-Dist: passlib[bcrypt]
Requires-Dist: aioredis
Requires-Dist: fastapi-limiter
Requires-Dist: passlib
Requires-Dist: pydantic-settings
Requires-Dist: python-jose
Requires-Dist: redis
Requires-Dist: starlette
Requires-Dist: toml
Requires-Dist: colorama
Requires-Dist: termcolor
